feincms3_language_sites/__init__.py
feincms3_language_sites/checks.py
feincms3_language_sites/middleware.py
feincms3_language_sites/models.py
feincms3_language_sites/locale/de/LC_MESSAGES/django.mo
feincms3_language_sites/locale/de/LC_MESSAGES/django.po
feincms3_language_sites/templatetags/__init__.py
feincms3_language_sites/templatetags/feincms3_language_sites.py
feincms3_language_sites-0.4.1.dist-info/METADATA
feincms3_language_sites-0.4.1.dist-info/WHEEL
feincms3_language_sites-0.4.1.dist-info/licenses/LICENSE
feincms3_language_sites-0.4.1.dist-info/RECORD
