Metadata-Version: 2.4
Name: feincms3-language-sites
Version: 0.4.1
Summary: Multisite support for feincms3
Project-URL: Homepage, https://github.com/matthiask/feincms3-language-sites/
Author-email: Matthias Kestenholz <mk@feinheit.ch>
License: BSD-3-Clause
License-File: LICENSE
Classifier: Environment :: Web Environment
Classifier: Framework :: Django
Classifier: Intended Audience :: Developers
Classifier: License :: OSI Approved :: BSD License
Classifier: Operating System :: OS Independent
Classifier: Programming Language :: Python
Classifier: Programming Language :: Python :: 3 :: Only
Classifier: Programming Language :: Python :: 3.10
Classifier: Programming Language :: Python :: 3.11
Classifier: Programming Language :: Python :: 3.12
Classifier: Programming Language :: Python :: 3.13
Classifier: Topic :: Internet :: WWW/HTTP :: Dynamic Content
Classifier: Topic :: Software Development
Classifier: Topic :: Software Development :: Libraries :: Application Frameworks
Requires-Python: >=3.10
Requires-Dist: django>=4.2
Requires-Dist: feincms3>=5.0a2
Provides-Extra: tests
Requires-Dist: coverage; extra == 'tests'
Requires-Dist: feincms3[all]; extra == 'tests'
